perform_topsis/102103699.py
Topsis_Saanvi_102103699-1.0.0.dist-info/LICENSE.unknown
Topsis_Saanvi_102103699-1.0.0.dist-info/METADATA
Topsis_Saanvi_102103699-1.0.0.dist-info/WHEEL
Topsis_Saanvi_102103699-1.0.0.dist-info/entry_points.txt
Topsis_Saanvi_102103699-1.0.0.dist-info/top_level.txt
Topsis_Saanvi_102103699-1.0.0.dist-info/RECORD
