Metadata-Version: 2.1
Name: Topsis-Saanvi-102103699
Version: 1.0.0
Summary: Performs TOPSIS
Home-page: https://github.com/Saanvi49/Topsis-Implementation
Author: Saanvi Sharma
Author-email: ssharma9_be21@thapar.edu
License: MIT
Classifier: License :: OSI Approved :: MIT License
Classifier: Programming Language :: Python :: 3.6
Classifier: Programming Language :: Python :: 3.7
Classifier: Programming Language :: Python :: 3.8
License-File: LICENSE.unknown
